{
  "page": 1,
  "total": 17,
  "records": 509,
  "rows": [
    {
      "id": "53461613",
      "cell": [
        "9/18/2024 1:09:47 PM",
        "MCW Online - 70671",
        "53461613",
        "Gift Card Envelopes (4008)",
        "1467",
        "4008",
        "<span><b>Location:</b></span>WHSE 1 > Q2",
        "N/A",
        "N/A",
        "wa577@mistercarwash.com",
        "",
        "091820241309481521",
        "0",
        "0",
        "",
        "Mister Car Wash",
        "1",
        "4",
        "Standard",
        "1",
        "0",
        "",
        "False",
        "True",
        "True"
      ]
    },
    {
      "id": "53461612",
      "cell": [
        "9/18/2024 1:09:47 PM",
        "MCW Online - 70671",
        "53461612",
        "Mister Gift Card (111494)",
        "1568",
        "111494",
        "<span><b>Location:</b></span>WHSE 1 > P1/Z12",
        "N/A",
        "N/A",
        "wa577@mistercarwash.com",
        "",
        "091820241309478442",
        "0",
        "0",
        "",
        "Mister Car Wash",
        "1",
        "4",
        "Standard",
        "1",
        "0",
        "",
        "False",
        "True",
        "True"
      ]
    },
    {
      "id": "53461520",
      "cell": [
        "9/18/2024 1:02:58 PM",
        "MCW Online - 70670",
        "53461520",
        "Titanium Exterior Comp Pass (26018)",
        "2998",
        "26018",
        "<span><b>Location:</b></span>WHSE 1>PENDING",
        "N/A",
        "N/A",
        "fl1802@mistercarwash.com",
        "",
        "091820241303002339",
        "091820241307384870",
        "0",
        "",
        "Mister Car Wash",
        "1",
        "4",
        "Standard",
        "1",
        "0",
        "",
        "False",
        "False",
        "True"
      ]
    },
    {
      "id": "53461519",
      "cell": [
        "9/18/2024 1:02:58 PM",
        "MCW Online - 70670",
        "53461519",
        "Curbside Windscreen Frame - 28x44 (11005)",
        "74",
        "11005",
        "<span><b>Location:</b></span>WHSE 2>",
        "N/A",
        "N/A",
        "fl1802@mistercarwash.com",
        "",
        "091820241302599913",
        "091820241307384870",
        "0",
        "",
        "Mister Car Wash",
        "1",
        "4",
        "Standard",
        "1",
        "0",
        "",
        "False",
        "False",
        "True"
      ]
    },
    {
      "id": "53461518",
      "cell": [
        "9/18/2024 1:02:58 PM",
        "MCW Online - 70670",
        "53461518",
        "Spring for Windmaster Frame (11014)",
        "299",
        "11014",
        "<span><b>Location:</b></span>WHSE 1>J2",
        "N/A",
        "N/A",
        "fl1802@mistercarwash.com",
        "",
        "091820241302598435",
        "091820241307384870",
        "0",
        "",
        "Mister Car Wash",
        "1",
        "4",
        "Standard",
        "1",
        "0",
        "",
        "False",
        "False",
        "True"
      ]
    },
    {
      "id": "53461517",
      "cell": [
        "9/18/2024 1:02:58 PM",
        "MCW Online - 70670",
        "53461517",
        "Titanium CSA Flash Cards (11308)",
        "2829",
        "11308",
        "<span><b>Location:</b></span>WHSE 1>Q3",
        "N/A",
        "N/A",
        "fl1802@mistercarwash.com",
        "",
        "091820241302596935",
        "091820241307384870",
        "0",
        "",
        "Mister Car Wash",
        "1",
        "4",
        "Standard",
        "1",
        "0",
        "",
        "False",
        "False",
        "True"
      ]
    },
    {
      "id": "53461516",
      "cell": [
        "9/18/2024 1:02:58 PM",
        "MCW Online - 70670",
        "53461516",
        "Blower Decal Sheet (9395)",
        "2368",
        "9395",
        "<span><b>Location:</b></span>WHSE 1>L2",
        "N/A",
        "N/A",
        "fl1802@mistercarwash.com",
        "",
        "091820241302595552",
        "091820241307384870",
        "0",
        "",
        "Mister Car Wash",
        "1",
        "4",
        "Standard",
        "1",
        "0",
        "",
        "False",
        "False",
        "True"
      ]
    },
    {
      "id": "53461514",
      "cell": [
        "9/18/2024 1:02:58 PM",
        "MCW Online - 70670",
        "53461514",
        "Mister Pen (111612)",
        "1767",
        "111612",
        "<span><b>Location:</b></span>WHSE 1>K3",
        "N/A",
        "N/A",
        "fl1802@mistercarwash.com",
        "",
        "091820241302592354",
        "091820241307384870",
        "0",
        "",
        "Mister Car Wash",
        "1",
        "4",
        "Standard",
        "1",
        "0",
        "",
        "False",
        "False",
        "True"
      ]
    },
    {
      "id": "53461515",
      "cell": [
        "9/18/2024 1:02:58 PM",
        "MCW Online - 70670",
        "53461515",
        "Mister Budget Board (111512) LF",
        "2397",
        "111512",
        "",
        "N/A",
        "N/A",
        "fl1802@mistercarwash.com",
        "",
        "091820241302593961",
        "091820241307384870",
        "0",
        "",
        "Mister Car Wash",
        "1",
        "0",
        "Standard",
        "1",
        "0",
        "",
        "False",
        "False",
        "True"
      ]
    },
    {
      "id": "53460039",
      "cell": [
        "9/18/2024 12:03:59 PM",
        "MCW Online - 70669",
        "53460039",
        "Base Exterior Fleet Wash Pass (16015)",
        "2714",
        "16015",
        "<br><span><b>Location:</b></span>WHSE 1 > U2",
        "N/A",
        "N/A",
        "Businessaccounts@mistercarwash.com",
        "",
        "091820241203597460",
        "091820241238450427",
        "0",
        "",
        "Mister Car Wash",
        "1",
        "4",
        "Standard",
        "1",
        "0",
        "",
        "False",
        "False",
        "True"
      ]
    },
    {
      "id": "53459887",
      "cell": [
        "9/18/2024 11:57:12 AM",
        "MCW Online - 70668",
        "53459887",
        "Titanium Exterior Comp Pass (26018)",
        "2998",
        "26018",
        "<span><b>Location:</b></span>WHSE 1>PENDING",
        "N/A",
        "N/A",
        "ia722@mistercarwash.com",
        "",
        "091820241157127280",
        "091820241201197610",
        "0",
        "",
        "Mister Car Wash",
        "1",
        "4",
        "Standard",
        "1",
        "0",
        "",
        "False",
        "False",
        "True"
      ]
    },
    {
      "id": "53459466",
      "cell": [
        "9/18/2024 11:32:49 AM",
        "MCW Online - 70667",
        "53459466",
        "Employee \"LOOKBOOK\" Appearance Guide (111547)",
        "1732",
        "111547",
        "<span><b>Location:</b></span>WHSE 1>S2",
        "N/A",
        "N/A",
        "tn831@mistercarwash.com",
        "",
        "091820241132503301",
        "091820241201041565",
        "0",
        "",
        "Mister Car Wash",
        "1",
        "4",
        "Standard",
        "1",
        "0",
        "",
        "False",
        "False",
        "True"
      ]
    },
    {
      "id": "53459465",
      "cell": [
        "9/18/2024 11:32:49 AM",
        "MCW Online - 70667",
        "53459465",
        "Titanium Exterior Comp Pass (26018)",
        "2998",
        "26018",
        "<span><b>Location:</b></span>WHSE 1>PENDING",
        "N/A",
        "N/A",
        "tn831@mistercarwash.com",
        "",
        "091820241132501711",
        "091820241201041565",
        "0",
        "",
        "Mister Car Wash",
        "1",
        "4",
        "Standard",
        "1",
        "0",
        "",
        "False",
        "False",
        "True"
      ]
    },
    {
      "id": "53459464",
      "cell": [
        "9/18/2024 11:32:49 AM",
        "MCW Online - 70667",
        "53459464",
        "Employee Handbooks - English (111545)",
        "1596",
        "111545",
        "<span><b>Location:</b></span>WHSE 1>U3",
        "N/A",
        "N/A",
        "tn831@mistercarwash.com",
        "",
        "091820241132500405",
        "091820241201041565",
        "0",
        "",
        "Mister Car Wash",
        "1",
        "4",
        "Standard",
        "1",
        "0",
        "",
        "False",
        "False",
        "True"
      ]
    },
    {
      "id": "53459463",
      "cell": [
        "9/18/2024 11:32:49 AM",
        "MCW Online - 70667",
        "53459463",
        "Wallmount Windscreen Frame - 28x44 (11003)",
        "72",
        "11003",
        "<span><b>Location:</b></span>WHSE 2>",
        "N/A",
        "N/A",
        "tn831@mistercarwash.com",
        "",
        "091820241132498979",
        "091820241201041565",
        "0",
        "",
        "Mister Car Wash",
        "1",
        "4",
        "Standard",
        "1",
        "0",
        "",
        "False",
        "False",
        "True"
      ]
    },
    {
      "id": "53459462",
      "cell": [
        "9/18/2024 11:32:49 AM",
        "MCW Online - 70667",
        "53459462",
        "Google Review Cling (23060) LF",
        "3633",
        "23060-TN - Tennessee_831",
        "Google Review Cling.Choose Your Location - TN - Tennessee_831",
        "N/A",
        "N/A",
        "tn831@mistercarwash.com",
        "",
        "091820241132497459",
        "091820241201041565",
        "0",
        "",
        "Mister Car Wash",
        "1",
        "1",
        "Standard",
        "1",
        "0",
        "",
        "False",
        "False",
        "True"
      ]
    },
    {
      "id": "53459461",
      "cell": [
        "9/18/2024 11:32:49 AM",
        "MCW Online - 70667",
        "53459461",
        "Business Card DIG",
        "8",
        "MCW-BC-Chris Turner",
        "Customized 3.5 x 2 business card. Digitally printed. - Chris Turner_615-451-0730_",
        "N/A",
        "N/A",
        "tn831@mistercarwash.com",
        "",
        "091820241132495160",
        "091820241201041565",
        "0",
        "",
        "Mister Car Wash",
        "1",
        "1",
        "Standard",
        "1",
        "0",
        "",
        "False",
        "False",
        "True"
      ]
    },
    {
      "id": "53459441",
      "cell": [
        "9/18/2024 11:31:12 AM",
        "MCW Online - 70666",
        "53459441",
        "Titanium Exterior Comp Pass (26018)",
        "2998",
        "26018",
        "<span><b>Location:</b></span>WHSE 1>PENDING",
        "N/A",
        "N/A",
        "fl1851@mistercarwash.com",
        "",
        "091820241131128708",
        "091820241200463413",
        "0",
        "",
        "Mister Car Wash",
        "1",
        "4",
        "Standard",
        "1",
        "0",
        "",
        "False",
        "False",
        "True"
      ]
    },
    {
      "id": "53459440",
      "cell": [
        "9/18/2024 11:31:12 AM",
        "MCW Online - 70666",
        "53459440",
        "Fundraising & Donations Card (21002)",
        "785",
        "21002",
        "<span><b>Location:</b></span>WHSE 1>Z18",
        "N/A",
        "N/A",
        "fl1851@mistercarwash.com",
        "",
        "091820241131125761",
        "091820241200463413",
        "0",
        "",
        "Mister Car Wash",
        "1",
        "4",
        "Standard",
        "1",
        "0",
        "",
        "False",
        "False",
        "True"
      ]
    },
    {
      "id": "53459443",
      "cell": [
        "9/18/2024 11:31:12 AM",
        "MCW Online - 70666",
        "53459443",
        "Business Card DIG",
        "8",
        "MCW-BC-Anthony Soto",
        "Customized 3.5 x 2 business card. Digitally printed. - Anthony Soto_9044130279_",
        "N/A",
        "N/A",
        "fl1851@mistercarwash.com",
        "",
        "091820241131132319",
        "091820241200463413",
        "0",
        "",
        "Mister Car Wash",
        "1",
        "1",
        "Standard",
        "1",
        "0",
        "",
        "False",
        "False",
        "True"
      ]
    },
    {
      "id": "53459442",
      "cell": [
        "9/18/2024 11:31:12 AM",
        "MCW Online - 70666",
        "53459442",
        "CSA Performance Board Express (111500) LF",
        "1572",
        "111500",
        "",
        "N/A",
        "N/A",
        "fl1851@mistercarwash.com",
        "",
        "091820241131130405",
        "091820241200463413",
        "0",
        "",
        "Mister Car Wash",
        "1",
        "0",
        "Standard",
        "1",
        "0",
        "",
        "False",
        "False",
        "True"
      ]
    },
    {
      "id": "53459349",
      "cell": [
        "9/18/2024 11:24:47 AM",
        "MCW Online - 70665",
        "53459349",
        "Titanium Exterior Comp Pass (26018)",
        "2998",
        "26018",
        "<span><b>Location:</b></span>WHSE 1>PENDING",
        "N/A",
        "N/A",
        "co033@mistercarwash.com",
        "",
        "091820241124481168",
        "091820241200295473",
        "0",
        "",
        "Mister Car Wash",
        "1",
        "4",
        "Standard",
        "1",
        "0",
        "",
        "False",
        "False",
        "True"
      ]
    },
    {
      "id": "53459348",
      "cell": [
        "9/18/2024 11:24:47 AM",
        "MCW Online - 70665",
        "53459348",
        "Curbside Windscreen Frame - 28x44 (11005)",
        "74",
        "11005",
        "<span><b>Location:</b></span>WHSE 2>",
        "N/A",
        "N/A",
        "co033@mistercarwash.com",
        "",
        "091820241124479369",
        "091820241200295473",
        "0",
        "",
        "Mister Car Wash",
        "1",
        "4",
        "Standard",
        "1",
        "0",
        "",
        "False",
        "False",
        "True"
      ]
    },
    {
      "id": "53457015",
      "cell": [
        "9/18/2024 10:36:31 AM",
        "MCW Online - 70664",
        "53457015",
        "Mister Chem Tag Set (21256)",
        "3248",
        "21256",
        "<span><b>Location:</b></span>WHSE 1 > M1",
        "N/A",
        "N/A",
        "az1322@mistercarwash.com",
        "",
        "091820241036323638",
        "091820241101032874",
        "0",
        "",
        "Mister Car Wash",
        "1",
        "4",
        "Standard",
        "1",
        "0",
        "",
        "False",
        "False",
        "True"
      ]
    },
    {
      "id": "53456609",
      "cell": [
        "9/18/2024 10:17:35 AM",
        "MCW Online - 70663",
        "53456609",
        "Pegasus Decal Set - Gen 2 EMV for Ingenico Self 4000 (4023)",
        "2962",
        "4023",
        "<span><b>Location:</b></span>WHSE 1>L2",
        "N/A",
        "N/A",
        "jkrebs@mistercarwash.com",
        "",
        "091820241017363550",
        "091820241100486234",
        "0",
        "",
        "Mister Car Wash",
        "1",
        "4",
        "Standard",
        "1",
        "0",
        "",
        "False",
        "False",
        "True"
      ]
    },
    {
      "id": "53456324",
      "cell": [
        "9/18/2024 10:05:45 AM",
        "MCW Online - 70662",
        "53456324",
        "Titanium CSA Flash Cards (11308)",
        "2829",
        "11308",
        "<span><b>Location:</b></span>WHSE 1>Q3",
        "N/A",
        "N/A",
        "tx003@mistercarwash.com",
        "",
        "091820241005459228",
        "091820241100339740",
        "0",
        "",
        "Mister Car Wash",
        "1",
        "4",
        "Standard",
        "1",
        "0",
        "",
        "False",
        "False",
        "True"
      ]
    },
    {
      "id": "53456325",
      "cell": [
        "9/18/2024 10:05:45 AM",
        "MCW Online - 70662",
        "53456325",
        "Titanium Interior Clean CSA Price Menu (21305) DIG",
        "2543",
        "21305-Austin | Mesquite",
        "Titan Interior Clean CSA Price Menu. Includes 2 Menu Cards held together with a ring. Choose your location. - Austin | Mesquite",
        "N/A",
        "N/A",
        "tx003@mistercarwash.com",
        "",
        "091820241005461482",
        "091820241100339740",
        "0",
        "",
        "Mister Car Wash",
        "1",
        "1",
        "Standard",
        "1",
        "0",
        "",
        "False",
        "False",
        "True"
      ]
    },
    {
      "id": "53454673",
      "cell": [
        "9/18/2024 9:05:54 AM",
        "MCW Online - 70661",
        "53454673",
        "Pegasus Decal Set - Gen 2 EMV for Ingenico Self 4000 (4023)",
        "2962",
        "4023",
        "<span><b>Location:</b></span>WHSE 1>L2",
        "N/A",
        "N/A",
        "jkrebs@mistercarwash.com",
        "",
        "091820240905550389",
        "091820241000323253",
        "0",
        "",
        "Mister Car Wash",
        "1",
        "4",
        "Standard",
        "1",
        "0",
        "",
        "False",
        "False",
        "True"
      ]
    },
    {
      "id": "53454527",
      "cell": [
        "9/18/2024 8:58:14 AM",
        "MCW Online - 70660",
        "53454527",
        "Daily Morning Huddle Pads (3004)",
        "1106",
        "3004",
        "<span><b>Location:</b></span>WHSE 1>Y1",
        "N/A",
        "N/A",
        "ga264@mistercarwash.com",
        "",
        "091820240858150439",
        "091820240901290743",
        "0",
        "",
        "Mister Car Wash",
        "1",
        "4",
        "Standard",
        "1",
        "0",
        "",
        "False",
        "False",
        "True"
      ]
    },
    {
      "id": "53454526",
      "cell": [
        "9/18/2024 8:58:14 AM",
        "MCW Online - 70660",
        "53454526",
        "Daily Morning Huddle Pads (3004)",
        "1106",
        "3004",
        "<span><b>Location:</b></span>WHSE 1>Y1",
        "N/A",
        "N/A",
        "ga264@mistercarwash.com",
        "",
        "091820240858148826",
        "091820240901290743",
        "0",
        "",
        "Mister Car Wash",
        "1",
        "4",
        "Standard",
        "1",
        "0",
        "",
        "False",
        "False",
        "True"
      ]
    }
  ],
  "userdata": {}
}
